setup.cfg
setup.py
bifocal/__init__.py
bifocal/bifocal.py
bifocal/utils.py
bifocal.egg-info/PKG-INFO
bifocal.egg-info/SOURCES.txt
bifocal.egg-info/dependency_links.txt
bifocal.egg-info/top_level.txt