Metadata-Version: 1.1
Name: bifocal
Version: 0.1.1
Summary: Automated FIFO and LIFO accounting for cryptocurrencies.
Home-page: https://github.com/frdwrd/bifocal
Author: James Prestwich
Author-email: james@storj.io
License: AGPLv3+
Download-URL: https://github.com/frdwrd/bifocal/archive/v0.1.1.tar.gz
Keywords: accounting bitcoin FIFO LIFO cryptocurrency
Platform: UNKNOWN
Classifier: Development Status :: 3 - Alpha
Classifier: Topic :: Utilities
Classifier: License :: OSI Approved :: GNU Affero General Public License v3
